mindspore_gl/__init__.py
mindspore_gl/array_kernel.cpython-39-aarch64-linux-gnu.so
mindspore_gl/array_kernel.py
mindspore_gl/bucket_kernel.cpython-39-aarch64-linux-gnu.so
mindspore_gl/memory_kernel.cpython-39-aarch64-linux-gnu.so
mindspore_gl/memory_kernel.py
mindspore_gl/sample_kernel.cpython-39-aarch64-linux-gnu.so
mindspore_gl/sample_kernel.py
mindspore_gl/version.py
mindspore_gl/backward/__init__.py
mindspore_gl/backward/csr_reduce_sum_net.py
mindspore_gl/backward/gather_net.py
mindspore_gl/dataloader/__init__.py
mindspore_gl/dataloader/dataloader.py
mindspore_gl/dataloader/dataset.py
mindspore_gl/dataloader/queue.py
mindspore_gl/dataloader/samplers.py
mindspore_gl/dataloader/split_data.py
mindspore_gl/dataloader/utils.py
mindspore_gl/dataloader/_utils/__init__.py
mindspore_gl/dataloader/_utils/concurrent_fetch.py
mindspore_gl/dataloader/_utils/fetch.py
mindspore_gl/dataloader/_utils/worker.py
mindspore_gl/dataloader/shared_numpy/__init__.py
mindspore_gl/dataloader/shared_numpy/_posixshmem.cpython-39-aarch64-linux-gnu.so
mindspore_gl/dataloader/shared_numpy/posixshmem.c
mindspore_gl/dataloader/shared_numpy/queue.py
mindspore_gl/dataloader/shared_numpy/reduction.py
mindspore_gl/dataloader/shared_numpy/shared_memory.py
mindspore_gl/dataloader/shared_numpy/shared_numpy.py
mindspore_gl/dataset/__init__.py
mindspore_gl/dataset/alchemy.py
mindspore_gl/dataset/base_dataset.py
mindspore_gl/dataset/blog_catalog.py
mindspore_gl/dataset/cora.py
mindspore_gl/dataset/enzymes.py
mindspore_gl/dataset/imdb_binary.py
mindspore_gl/dataset/mag240m.py
mindspore_gl/dataset/metr_la.py
mindspore_gl/dataset/ppi.py
mindspore_gl/dataset/reddit.py
mindspore_gl/dataset/utils.py
mindspore_gl/extensions/__init__.py
mindspore_gl/extensions/array_kernel.pyx
mindspore_gl/extensions/buckize.c
mindspore_gl/extensions/memory_reference_counter.pyx
mindspore_gl/extensions/sample_kernel.pyx
mindspore_gl/graph/__init__.py
mindspore_gl/graph/csr_convert.py
mindspore_gl/graph/gcn_norm.py
mindspore_gl-0.2.dist-info/LICENSE
mindspore_gl-0.2.dist-info/METADATA
mindspore_gl-0.2.dist-info/WHEEL
mindspore_gl-0.2.dist-info/top_level.txt
mindspore_gl-0.2.dist-info/RECORD
